nicegui_ugform/__init__.py
nicegui_ugform/core/__init__.py
nicegui_ugform/core/fields.py
nicegui_ugform/core/form.py
nicegui_ugform/i18n/__init__.py
nicegui_ugform/i18n/helper.py
nicegui_ugform/i18n/keys.py
nicegui_ugform/i18n/locale_en.py
nicegui_ugform/i18n/locale_zh_cn.py
nicegui_ugform/ui/__init__.py
nicegui_ugform/ui/form_display.py
nicegui_ugform/ui/form_editor.py
nicegui_ugform-1.1.1.dist-info/licenses/LICENSE
nicegui_ugform-1.1.1.dist-info/METADATA
nicegui_ugform-1.1.1.dist-info/WHEEL
nicegui_ugform-1.1.1.dist-info/RECORD
