Metadata-Version: 2.4
Name: NiceGui-UGForm
Version: 1.1.1
Summary: User Generated Form Component for NiceGUI Framework
License: MIT
License-File: LICENSE
Author: Harry Huang
Author-email: harryhuang2652@qq.com
Requires-Python: >=3.9,<4
Classifier: Programming Language :: Python :: 3
Classifier: License :: OSI Approved :: MIT License
Classifier: Operating System :: OS Independent
Requires-Dist: nicegui (>=3.0,<4)
Project-URL: Repository, https://github.com/isHarryh/NiceGUI-UGForm
